picachain/__init__.py
picachain/chains/__init__.py
picachain/chains/chain.py
picachain/chains/image/search.py
picachain/chains/unstructured/__init__.py
picachain/chains/unstructured/charts.py
picachain/datastore/__init__.py
picachain/datastore/chroma.py
picachain/datastore/datastore.py
picachain/datastore/pinecone.py
picachain/embedding/__init__.py
picachain/embedding/clip_embedding.py
picachain/embedding/embedding.py
picachain/generation/__init__.py
picachain/generation/text2image.py
picachain/models/__init__.py
picachain/models/deplot/__init__.py
picachain/models/deplot/deplot.py
picachain/models/donut/__init__.py
picachain/models/donut/classification.py
picachain/models/donut/cord.py
picachain/models/donut/docvqa.py
picachain/models/llava/__init__.py
picachain/models/llava/llava.py
picachain/models/openai/__init__.py
picachain/models/openai/openai.py
picachain/pydantic.py
picachain/retriever/__init__.py
picachain/retriever/image_retriever.py
picachain/retriever/retriever.py
picachain/unstructured/__init__.py
picachain/unstructured/charts.py
picachain/unstructured/tables.py
picachain/utils/image_util.py
picachain-0.1.37.dist-info/LICENSE
picachain-0.1.37.dist-info/METADATA
picachain-0.1.37.dist-info/WHEEL
picachain-0.1.37.dist-info/RECORD
