Metadata-Version: 2.1
Name: picachain
Version: 0.1.37
Summary: Build quick LLM pipelines for image specific tasks.
Home-page: https://github.com/d1pankarmedhi/picachain
License: MIT
Keywords: python,search-engine,chromadb,image,search,packages,poetry,python-packages,pinecone
Author: d1pankarmedhi
Author-email: dipankarmedhi11@gmail.com
Requires-Python: >=3.10,<4.0
Classifier: License :: OSI Approved :: MIT License
Classifier: Programming Language :: Python :: 3
Classifier: Programming Language :: Python :: 3.10
Classifier: Programming Language :: Python :: 3.11
Classifier: Programming Language :: Python :: 3.12
Requires-Dist: chromadb (>=0.4.24,<0.5.0)
Requires-Dist: idna (==3.7)
Requires-Dist: matplotlib (>=3.8.3,<4.0.0)
Requires-Dist: pillow (==10.3.0)
Requires-Dist: pinecone-client (>=3.2.1,<4.0.0)
Requires-Dist: pysqlite3-binary (>=0.5.2.post3,<0.6.0)
Project-URL: Repository, https://github.com/d1pankarmedhi/picachain
